[
  {
    "op": "core/mass-edit",
    "engineConfig": {
      "facets": [
        {
          "type": "list",
          "name": "project",
          "expression": "value",
          "columnName": "project",
          "invert": false,
          "omitBlank": false,
          "omitError": false,
          "selection": [
            {
              "v": {
                "v": "NIH Roadmap Epigenomics",
                "l": "NIH Roadmap Epigenomics"
              }
            }
          ],
          "selectBlank": false,
          "selectError": false
        },
        {
          "type": "list",
          "name": "cell_type",
          "expression": "value",
          "columnName": "cell_type",
          "invert": false,
          "omitBlank": false,
          "omitError": false,
          "selection": [
            {
              "v": {
                "v": "common myeloid progenitor, cd34-positive",
                "l": "common myeloid progenitor, cd34-positive"
              }
            }
          ],
          "selectBlank": false,
          "selectError": false
        }
      ],
      "mode": "row-based"
    },
    "columnName": "markers",
    "expression": "value",
    "edits": [
      {
        "from": [],
        "fromBlank": true,
        "fromError": false,
        "to": "CD34+"
      }
    ],
    "description": "Mass edit cells in column markers"
  },
  {
    "op": "core/mass-edit",
    "engineConfig": {
      "facets": [
        {
          "type": "list",
          "name": "cell_type",
          "expression": "value",
          "columnName": "cell_type",
          "invert": false,
          "omitBlank": false,
          "omitError": false,
          "selection": [
            {
              "v": {
                "v": "cd14-positive monocyte",
                "l": "cd14-positive monocyte"
              }
            }
          ],
          "selectBlank": false,
          "selectError": false
        }
      ],
      "mode": "row-based"
    },
    "columnName": "markers",
    "expression": "value",
    "edits": [
      {
        "from": [],
        "fromBlank": true,
        "fromError": false,
        "to": "CD14+"
      }
    ],
    "description": "Mass edit cells in column markers"
  },
  {
    "op": "core/mass-edit",
    "engineConfig": {
      "facets": [],
      "mode": "row-based"
    },
    "columnName": "cell_type",
    "expression": "value",
    "edits": [
      {
        "from": [
          "neurosphere"
        ],
        "fromBlank": false,
        "fromError": false,
        "to": "neuronal stem cell"
      }
    ],
    "description": "Mass edit cells in column cell_type"
  },
  {
    "op": "core/mass-edit",
    "engineConfig": {
      "facets": [
        {
          "type": "list",
          "name": "cell_type",
          "expression": "value",
          "columnName": "cell_type",
          "invert": false,
          "omitBlank": false,
          "omitError": false,
          "selection": [
            {
              "v": {
                "v": "effector memory cd4-positive, alpha-beta t cell",
                "l": "effector memory cd4-positive, alpha-beta t cell"
              }
            }
          ],
          "selectBlank": false,
          "selectError": false
        }
      ],
      "mode": "row-based"
    },
    "columnName": "markers",
    "expression": "value",
    "edits": [
      {
        "from": [],
        "fromBlank": true,
        "fromError": false,
        "to": "CD4+"
      }
    ],
    "description": "Mass edit cells in column markers"
  },
  {
    "op": "core/mass-edit",
    "engineConfig": {
      "facets": [
        {
          "type": "list",
          "name": "cell_type",
          "expression": "value",
          "columnName": "cell_type",
          "invert": false,
          "omitBlank": false,
          "omitError": false,
          "selection": [
            {
              "v": {
                "v": "cd8-positive, alpha-beta memory t cell",
                "l": "cd8-positive, alpha-beta memory t cell"
              }
            }
          ],
          "selectBlank": false,
          "selectError": false
        }
      ],
      "mode": "row-based"
    },
    "columnName": "markers",
    "expression": "value",
    "edits": [
      {
        "from": [],
        "fromBlank": true,
        "fromError": false,
        "to": "CD8+"
      }
    ],
    "description": "Mass edit cells in column markers"
  },
  {
    "op": "core/mass-edit",
    "engineConfig": {
      "facets": [
        {
          "type": "list",
          "name": "cell_type",
          "expression": "value",
          "columnName": "cell_type",
          "invert": false,
          "omitBlank": false,
          "omitError": false,
          "selection": [
            {
              "v": {
                "v": "cd4-positive, cd25-positive, alpha-beta regulatory t cell",
                "l": "cd4-positive, cd25-positive, alpha-beta regulatory t cell"
              }
            }
          ],
          "selectBlank": false,
          "selectError": false
        },
        {
          "type": "text",
          "name": "EpiRR",
          "columnName": "EpiRR",
          "query": "",
          "mode": "text",
          "caseSensitive": false,
          "invert": false
        }
      ],
      "mode": "row-based"
    },
    "columnName": "markers",
    "expression": "value",
    "edits": [
      {
        "from": [],
        "fromBlank": true,
        "fromError": false,
        "to": "CD4+ CD25+"
      }
    ],
    "description": "Mass edit cells in column markers"
  },
  {
    "op": "core/mass-edit",
    "engineConfig": {
      "facets": [
        {
          "type": "list",
          "name": "cell_type",
          "expression": "value",
          "columnName": "cell_type",
          "invert": false,
          "omitBlank": false,
          "omitError": false,
          "selection": [
            {
              "v": {
                "v": "cd4-positive, alpha-beta t cell",
                "l": "cd4-positive, alpha-beta t cell"
              }
            }
          ],
          "selectBlank": false,
          "selectError": false
        },
        {
          "type": "text",
          "name": "EpiRR",
          "columnName": "EpiRR",
          "query": "",
          "mode": "text",
          "caseSensitive": false,
          "invert": false
        }
      ],
      "mode": "row-based"
    },
    "columnName": "markers",
    "expression": "value",
    "edits": [
      {
        "from": [],
        "fromBlank": true,
        "fromError": false,
        "to": "CD4+"
      }
    ],
    "description": "Mass edit cells in column markers"
  },
  {
    "op": "core/mass-edit",
    "engineConfig": {
      "facets": [
        {
          "type": "list",
          "name": "cell_type",
          "expression": "value",
          "columnName": "cell_type",
          "invert": false,
          "omitBlank": false,
          "omitError": false,
          "selection": [
            {
              "v": {
                "v": "cd4-positive alpha-beta memory t cell",
                "l": "cd4-positive alpha-beta memory t cell"
              }
            }
          ],
          "selectBlank": false,
          "selectError": false
        }
      ],
      "mode": "row-based"
    },
    "columnName": "markers",
    "expression": "value",
    "edits": [
      {
        "from": [],
        "fromBlank": true,
        "fromError": false,
        "to": "CD4+"
      }
    ],
    "description": "Mass edit cells in column markers"
  },
  {
    "op": "core/mass-edit",
    "engineConfig": {
      "facets": [
        {
          "type": "list",
          "name": "cell_type",
          "expression": "value",
          "columnName": "cell_type",
          "invert": false,
          "omitBlank": false,
          "omitError": false,
          "selection": [
            {
              "v": {
                "v": "naive thymus-derived CD4-positive, alpha-beta T cell",
                "l": "naive thymus-derived CD4-positive, alpha-beta T cell"
              }
            }
          ],
          "selectBlank": false,
          "selectError": false
        }
      ],
      "mode": "row-based"
    },
    "columnName": "markers",
    "expression": "value",
    "edits": [
      {
        "from": [],
        "fromBlank": true,
        "fromError": false,
        "to": "CD4+"
      }
    ],
    "description": "Mass edit cells in column markers"
  },
  {
    "op": "core/mass-edit",
    "engineConfig": {
      "facets": [
        {
          "type": "list",
          "name": "cell_type",
          "expression": "value",
          "columnName": "cell_type",
          "invert": false,
          "omitBlank": false,
          "omitError": false,
          "selection": [
            {
              "v": {
                "v": "cd8-positive, alpha-beta t cell",
                "l": "cd8-positive, alpha-beta t cell"
              }
            }
          ],
          "selectBlank": false,
          "selectError": false
        }
      ],
      "mode": "row-based"
    },
    "columnName": "markers",
    "expression": "value",
    "edits": [
      {
        "from": [],
        "fromBlank": true,
        "fromError": false,
        "to": "CD8+"
      }
    ],
    "description": "Mass edit cells in column markers"
  }
]