[
  {
    "op": "core/mass-edit",
    "engineConfig": {
      "facets": [],
      "mode": "row-based"
    },
    "columnName": "tissue_type",
    "expression": "value",
    "edits": [
      {
        "from": [
          "bone marrow?"
        ],
        "fromBlank": false,
        "fromError": false,
        "to": "mononuclear cell of bone marrow"
      }
    ],
    "description": "Mass edit cells in column tissue_type"
  },
  {
    "op": "core/mass-edit",
    "engineConfig": {
      "facets": [
        {
          "type": "text",
          "name": "tissue_type",
          "columnName": "tissue_type",
          "query": "?",
          "mode": "text",
          "caseSensitive": false,
          "invert": false
        }
      ],
      "mode": "row-based"
    },
    "columnName": "tissue_type",
    "expression": "value",
    "edits": [
      {
        "from": [
          "future brain?"
        ],
        "fromBlank": false,
        "fromError": false,
        "to": "germinal neuroepithelium"
      }
    ],
    "description": "Mass edit cells in column tissue_type"
  },
  {
    "op": "core/mass-edit",
    "engineConfig": {
      "facets": [
        {
          "type": "text",
          "name": "tissue_type",
          "columnName": "tissue_type",
          "query": "?",
          "mode": "text",
          "caseSensitive": false,
          "invert": false
        }
      ],
      "mode": "row-based"
    },
    "columnName": "tissue_type",
    "expression": "value",
    "edits": [
      {
        "from": [
          "sigmoid colon?"
        ],
        "fromBlank": false,
        "fromError": false,
        "to": "sigmoid colon"
      }
    ],
    "description": "Mass edit cells in column tissue_type"
  },
  {
    "op": "core/mass-edit",
    "engineConfig": {
      "facets": [],
      "mode": "row-based"
    },
    "columnName": "markers",
    "expression": "value",
    "edits": [
      {
        "from": [
          "popolazione patologica (gate 89% circa) CD34+ HLA-DR+ CD19+"
        ],
        "fromBlank": false,
        "fromError": false,
        "to": "pathological population (gate 89%) CD34+ HLA-DR+ CD19+"
      }
    ],
    "description": "Mass edit cells in column markers"
  },
  {
    "op": "core/mass-edit",
    "engineConfig": {
      "facets": [
        {
          "type": "list",
          "name": "cell_type",
          "expression": "value",
          "columnName": "cell_type",
          "invert": false,
          "omitBlank": false,
          "omitError": false,
          "selection": [
            {
              "v": {
                "v": "b cell",
                "l": "b cell"
              }
            }
          ],
          "selectBlank": false,
          "selectError": false
        }
      ],
      "mode": "row-based"
    },
    "columnName": "sample_ontology_term",
    "expression": "value",
    "edits": [
      {
        "from": [],
        "fromBlank": true,
        "fromError": false,
        "to": "cl:0000236"
      }
    ],
    "description": "Mass edit cells in column sample_ontology_term"
  },
  {
    "op": "core/mass-edit",
    "engineConfig": {
      "facets": [
        {
          "type": "list",
          "name": "cell_type",
          "expression": "value",
          "columnName": "cell_type",
          "invert": false,
          "omitBlank": false,
          "omitError": false,
          "selection": [
            {
              "v": {
                "v": "b cell",
                "l": "b cell"
              }
            }
          ],
          "selectBlank": false,
          "selectError": false
        }
      ],
      "mode": "row-based"
    },
    "columnName": "sample_ontology_term",
    "expression": "value",
    "edits": [
      {
        "from": [
          "cl:0000236::cl:2000006"
        ],
        "fromBlank": false,
        "fromError": false,
        "to": "cl:2000006"
      }
    ],
    "description": "Mass edit cells in column sample_ontology_term"
  },
  {
    "op": "core/mass-edit",
    "engineConfig": {
      "facets": [
        {
          "type": "list",
          "name": "sample_ontology_term",
          "expression": "value",
          "columnName": "sample_ontology_term",
          "invert": false,
          "omitBlank": false,
          "omitError": false,
          "selection": [
            {
              "v": {
                "v": "zfa:0009115",
                "l": "zfa:0009115"
              }
            }
          ],
          "selectBlank": false,
          "selectError": false
        }
      ],
      "mode": "row-based"
    },
    "columnName": "sample_ontology_term",
    "expression": "value",
    "edits": [
      {
        "from": [
          "zfa:0009115"
        ],
        "fromBlank": false,
        "fromError": false,
        "to": "cl:0000187"
      }
    ],
    "description": "Mass edit cells in column sample_ontology_term"
  },
  {
    "op": "core/mass-edit",
    "engineConfig": {
      "facets": [
        {
          "type": "list",
          "name": "sample_ontology_term",
          "expression": "value",
          "columnName": "sample_ontology_term",
          "invert": false,
          "omitBlank": false,
          "omitError": false,
          "selection": [
            {
              "v": {
                "v": "cl:0000187",
                "l": "cl:0000187"
              }
            }
          ],
          "selectBlank": false,
          "selectError": false
        }
      ],
      "mode": "row-based"
    },
    "columnName": "phenotype",
    "expression": "value",
    "edits": [
      {
        "from": [
          "EFO_0000609"
        ],
        "fromBlank": false,
        "fromError": false,
        "to": ""
      }
    ],
    "description": "Mass edit cells in column phenotype"
  },
  {
    "op": "core/mass-edit",
    "engineConfig": {
      "facets": [
        {
          "type": "list",
          "name": "cell_type",
          "expression": "value",
          "columnName": "cell_type",
          "invert": false,
          "omitBlank": false,
          "omitError": false,
          "selection": [
            {
              "v": {
                "v": "b cell from peripheral blood",
                "l": "b cell from peripheral blood"
              }
            }
          ],
          "selectBlank": false,
          "selectError": false
        }
      ],
      "mode": "row-based"
    },
    "columnName": "tissue_type",
    "expression": "value",
    "edits": [
      {
        "from": [],
        "fromBlank": true,
        "fromError": false,
        "to": "venous blood"
      }
    ],
    "description": "Mass edit cells in column tissue_type"
  },
  {
    "op": "core/mass-edit",
    "engineConfig": {
      "facets": [],
      "mode": "row-based"
    },
    "columnName": "cell_type",
    "expression": "value",
    "edits": [
      {
        "from": [
          "b cell from peripheral blood"
        ],
        "fromBlank": false,
        "fromError": false,
        "to": "b cell"
      }
    ],
    "description": "Mass edit cells in column cell_type"
  },
  {
    "op": "core/mass-edit",
    "engineConfig": {
      "facets": [],
      "mode": "row-based"
    },
    "columnName": "cell_type",
    "expression": "value",
    "edits": [
      {
        "from": [
          "renal artery endothelial cells"
        ],
        "fromBlank": false,
        "fromError": false,
        "to": "arcuate artery endothelial cells"
      }
    ],
    "description": "Mass edit cells in column cell_type"
  },
  {
    "op": "core/mass-edit",
    "engineConfig": {
      "facets": [
        {
          "type": "text",
          "name": "cell_type",
          "columnName": "cell_type",
          "query": "cytotrophoblast",
          "mode": "text",
          "caseSensitive": false,
          "invert": false
        },
        {
          "type": "list",
          "name": "project",
          "expression": "value",
          "columnName": "project",
          "invert": false,
          "omitBlank": false,
          "omitError": false,
          "selection": [
            {
              "v": {
                "v": "CEEHRC",
                "l": "CEEHRC"
              }
            }
          ],
          "selectBlank": false,
          "selectError": false
        }
      ],
      "mode": "row-based"
    },
    "columnName": "cell_type",
    "expression": "value",
    "edits": [
      {
        "from": [
          "cytotrophoblast cell"
        ],
        "fromBlank": false,
        "fromError": false,
        "to": "mononuclear cytotrophoblast cell"
      }
    ],
    "description": "Mass edit cells in column cell_type"
  },
  {
    "op": "core/mass-edit",
    "engineConfig": {
      "facets": [
        {
          "type": "text",
          "name": "cell_type",
          "columnName": "cell_type",
          "query": "cytotrophoblast",
          "mode": "text",
          "caseSensitive": false,
          "invert": false
        },
        {
          "type": "list",
          "name": "project",
          "expression": "value",
          "columnName": "project",
          "invert": false,
          "omitBlank": false,
          "omitError": false,
          "selection": [
            {
              "v": {
                "v": "AMED-CREST",
                "l": "AMED-CREST"
              }
            }
          ],
          "selectBlank": false,
          "selectError": false
        }
      ],
      "mode": "row-based"
    },
    "columnName": "cell_type",
    "expression": "value",
    "edits": [
      {
        "from": [
          "cd49f_positive_cytotrophoblast"
        ],
        "fromBlank": false,
        "fromError": false,
        "to": "trophoblast"
      }
    ],
    "description": "Mass edit cells in column cell_type"
  },
  {
    "op": "core/mass-edit",
    "engineConfig": {
      "facets": [
        {
          "type": "text",
          "name": "cell_type",
          "columnName": "cell_type",
          "query": "cytotrophoblast",
          "mode": "text",
          "caseSensitive": false,
          "invert": false
        },
        {
          "type": "list",
          "name": "project",
          "expression": "value",
          "columnName": "project",
          "invert": false,
          "omitBlank": false,
          "omitError": false,
          "selection": [
            {
              "v": {
                "v": "AMED-CREST",
                "l": "AMED-CREST"
              }
            }
          ],
          "selectBlank": false,
          "selectError": false
        }
      ],
      "mode": "row-based"
    },
    "columnName": "cell_type",
    "expression": "value",
    "edits": [
      {
        "from": [
          "cytotrophoblast cell"
        ],
        "fromBlank": false,
        "fromError": false,
        "to": "trophoblast cell"
      }
    ],
    "description": "Mass edit cells in column cell_type"
  },
  {
    "op": "core/mass-edit",
    "engineConfig": {
      "facets": [
        {
          "type": "text",
          "name": "cell_type",
          "columnName": "cell_type",
          "query": "cytotrophoblast",
          "mode": "text",
          "caseSensitive": false,
          "invert": false
        },
        {
          "type": "list",
          "name": "project",
          "expression": "value",
          "columnName": "project",
          "invert": false,
          "omitBlank": false,
          "omitError": false,
          "selection": [
            {
              "v": {
                "v": "AMED-CREST",
                "l": "AMED-CREST"
              }
            }
          ],
          "selectBlank": false,
          "selectError": false
        }
      ],
      "mode": "row-based"
    },
    "columnName": "cell_type",
    "expression": "value",
    "edits": [
      {
        "from": [
          "hla-g_positive_extravillous_cytotrophoblast"
        ],
        "fromBlank": false,
        "fromError": false,
        "to": "trophoblast cell"
      }
    ],
    "description": "Mass edit cells in column cell_type"
  },
  {
    "op": "core/mass-edit",
    "engineConfig": {
      "facets": [
        {
          "type": "text",
          "name": "cell_type",
          "columnName": "cell_type",
          "query": "trophoblast",
          "mode": "text",
          "caseSensitive": false,
          "invert": false
        },
        {
          "type": "list",
          "name": "project",
          "expression": "value",
          "columnName": "project",
          "invert": false,
          "omitBlank": false,
          "omitError": false,
          "selection": [
            {
              "v": {
                "v": "AMED-CREST",
                "l": "AMED-CREST"
              }
            }
          ],
          "selectBlank": false,
          "selectError": false
        }
      ],
      "mode": "row-based"
    },
    "columnName": "cell_type",
    "expression": "value",
    "edits": [
      {
        "from": [
          "trophoblast"
        ],
        "fromBlank": false,
        "fromError": false,
        "to": "trophoblast cell"
      }
    ],
    "description": "Mass edit cells in column cell_type"
  },
  {
    "op": "core/mass-edit",
    "engineConfig": {
      "facets": [
        {
          "type": "text",
          "name": "cell_type",
          "columnName": "cell_type",
          "query": "trophoblast",
          "mode": "text",
          "caseSensitive": false,
          "invert": false
        },
        {
          "type": "list",
          "name": "project",
          "expression": "value",
          "columnName": "project",
          "invert": false,
          "omitBlank": false,
          "omitError": false,
          "selection": [
            {
              "v": {
                "v": "AMED-CREST",
                "l": "AMED-CREST"
              }
            }
          ],
          "selectBlank": false,
          "selectError": false
        }
      ],
      "mode": "row-based"
    },
    "columnName": "cell_type",
    "expression": "value",
    "edits": [
      {
        "from": [
          "trophoblast stem cell"
        ],
        "fromBlank": false,
        "fromError": false,
        "to": "trophoblast cell"
      }
    ],
    "description": "Mass edit cells in column cell_type"
  },
  {
    "op": "core/mass-edit",
    "engineConfig": {
      "facets": [
        {
          "type": "list",
          "name": "cell_type",
          "expression": "value",
          "columnName": "cell_type",
          "invert": false,
          "omitBlank": false,
          "omitError": false,
          "selection": [
            {
              "v": {
                "v": "cord blood",
                "l": "cord blood"
              }
            }
          ],
          "selectBlank": false,
          "selectError": false
        }
      ],
      "mode": "row-based"
    },
    "columnName": "biomaterial_type",
    "expression": "value",
    "edits": [
      {
        "from": [
          "primary cell"
        ],
        "fromBlank": false,
        "fromError": false,
        "to": "primary tissue"
      }
    ],
    "description": "Mass edit cells in column biomaterial_type"
  },
  {
    "op": "core/mass-edit",
    "engineConfig": {
      "facets": [
        {
          "type": "list",
          "name": "cell_type",
          "expression": "value",
          "columnName": "cell_type",
          "invert": false,
          "omitBlank": false,
          "omitError": false,
          "selection": [
            {
              "v": {
                "v": "cord blood",
                "l": "cord blood"
              }
            }
          ],
          "selectBlank": false,
          "selectError": false
        }
      ],
      "mode": "row-based"
    },
    "columnName": "tissue_type",
    "expression": "value",
    "edits": [
      {
        "from": [],
        "fromBlank": true,
        "fromError": false,
        "to": "umbilical cord blood"
      }
    ],
    "description": "Mass edit cells in column tissue_type"
  },
  {
    "op": "core/mass-edit",
    "engineConfig": {
      "facets": [
        {
          "type": "list",
          "name": "cell_type",
          "expression": "value",
          "columnName": "cell_type",
          "invert": false,
          "omitBlank": false,
          "omitError": false,
          "selection": [
            {
              "v": {
                "v": "cord blood",
                "l": "cord blood"
              }
            }
          ],
          "selectBlank": false,
          "selectError": false
        }
      ],
      "mode": "row-based"
    },
    "columnName": "sample_ontology_term",
    "expression": "value",
    "edits": [
      {
        "from": [
          "cl:0000081"
        ],
        "fromBlank": false,
        "fromError": false,
        "to": "uberon:0012168"
      }
    ],
    "description": "Mass edit cells in column sample_ontology_term"
  },
  {
    "op": "core/mass-edit",
    "engineConfig": {
      "facets": [],
      "mode": "row-based"
    },
    "columnName": "cell_type",
    "expression": "value",
    "edits": [
      {
        "from": [
          "cord blood"
        ],
        "fromBlank": false,
        "fromError": false,
        "to": ""
      }
    ],
    "description": "Mass edit cells in column cell_type"
  },
  {
    "op": "core/mass-edit",
    "engineConfig": {
      "facets": [],
      "mode": "row-based"
    },
    "columnName": "cell_type",
    "expression": "value",
    "edits": [
      {
        "from": [
          "cord blood progenitors"
        ],
        "fromBlank": false,
        "fromError": false,
        "to": "CD34-positive, CD38-negative hematopoietic stem cell"
      }
    ],
    "description": "Mass edit cells in column cell_type"
  },
  {
    "op": "core/mass-edit",
    "engineConfig": {
      "facets": [
        {
          "type": "list",
          "name": "cell_type",
          "expression": "value",
          "columnName": "cell_type",
          "invert": false,
          "omitBlank": false,
          "omitError": false,
          "selection": [
            {
              "v": {
                "v": "blastocyst",
                "l": "blastocyst"
              }
            }
          ],
          "selectBlank": false,
          "selectError": false
        }
      ],
      "mode": "row-based"
    },
    "columnName": "sample_ontology_term",
    "expression": "value",
    "edits": [
      {
        "from": [],
        "fromBlank": true,
        "fromError": false,
        "to": "cl:0002321"
      }
    ],
    "description": "Mass edit cells in column sample_ontology_term"
  },
  {
    "op": "core/mass-edit",
    "engineConfig": {
      "facets": [
        {
          "type": "list",
          "name": "cell_type",
          "expression": "value",
          "columnName": "cell_type",
          "invert": false,
          "omitBlank": false,
          "omitError": false,
          "selection": [
            {
              "v": {
                "v": "blastocyst",
                "l": "blastocyst"
              }
            }
          ],
          "selectBlank": false,
          "selectError": false
        }
      ],
      "mode": "row-based"
    },
    "columnName": "cell_type",
    "expression": "value",
    "edits": [
      {
        "from": [
          "blastocyst"
        ],
        "fromBlank": false,
        "fromError": false,
        "to": "embryonic cell (metazoa)"
      }
    ],
    "description": "Mass edit cells in column cell_type"
  },
  {
    "op": "core/mass-edit",
    "engineConfig": {
      "facets": [
        {
          "type": "list",
          "name": "cell_type",
          "expression": "value",
          "columnName": "cell_type",
          "invert": false,
          "omitBlank": false,
          "omitError": false,
          "selection": [
            {
              "v": {
                "v": "endometrial_epithelium_follicular_phase",
                "l": "endometrial_epithelium_follicular_phase"
              }
            }
          ],
          "selectBlank": false,
          "selectError": false
        }
      ],
      "mode": "row-based"
    },
    "columnName": "sample_ontology_term",
    "expression": "value",
    "edits": [
      {
        "from": [],
        "fromBlank": true,
        "fromError": false,
        "to": "cl:0002327"
      }
    ],
    "description": "Mass edit cells in column sample_ontology_term"
  },
  {
    "op": "core/mass-edit",
    "engineConfig": {
      "facets": [
        {
          "type": "list",
          "name": "cell_type",
          "expression": "value",
          "columnName": "cell_type",
          "invert": false,
          "omitBlank": false,
          "omitError": false,
          "selection": [
            {
              "v": {
                "v": "endometrial_epithelium_follicular_phase",
                "l": "endometrial_epithelium_follicular_phase"
              }
            }
          ],
          "selectBlank": false,
          "selectError": false
        }
      ],
      "mode": "row-based"
    },
    "columnName": "sample_ontology_term",
    "expression": "value",
    "edits": [
      {
        "from": [
          "cl:0002327"
        ],
        "fromBlank": false,
        "fromError": false,
        "to": "cl:0009084"
      }
    ],
    "description": "Mass edit cells in column sample_ontology_term"
  },
  {
    "op": "core/mass-edit",
    "engineConfig": {
      "facets": [],
      "mode": "row-based"
    },
    "columnName": "cell_type",
    "expression": "value",
    "edits": [
      {
        "from": [
          "endometrial_epithelium_follicular_phase"
        ],
        "fromBlank": false,
        "fromError": false,
        "to": "epithelial cell of endometrial gland"
      }
    ],
    "description": "Mass edit cells in column cell_type"
  },
  {
    "op": "core/mass-edit",
    "engineConfig": {
      "facets": [],
      "mode": "row-based"
    },
    "columnName": "cell_type",
    "expression": "value",
    "edits": [
      {
        "from": [
          "naive cd4-positive t cell"
        ],
        "fromBlank": false,
        "fromError": false,
        "to": "naive thymus-derived CD4-positive, alpha-beta T cell"
      }
    ],
    "description": "Mass edit cells in column cell_type"
  },
  {
    "op": "core/mass-edit",
    "engineConfig": {
      "facets": [],
      "mode": "row-based"
    },
    "columnName": "cell_type",
    "expression": "value",
    "edits": [
      {
        "from": [
          "naive thymus-derived cd4-positive, alpha-beta t cell"
        ],
        "fromBlank": false,
        "fromError": false,
        "to": "naive thymus-derived CD4-positive, alpha-beta T cell"
      }
    ],
    "description": "Mass edit cells in column cell_type"
  },
  {
    "op": "core/mass-edit",
    "engineConfig": {
      "facets": [
        {
          "type": "list",
          "name": "cell_type",
          "expression": "value",
          "columnName": "cell_type",
          "invert": false,
          "omitBlank": false,
          "omitError": false,
          "selection": [
            {
              "v": {
                "v": "naive cd4+ t cells",
                "l": "naive cd4+ t cells"
              }
            }
          ],
          "selectBlank": false,
          "selectError": false
        }
      ],
      "mode": "row-based"
    },
    "columnName": "sample_ontology_term",
    "expression": "value",
    "edits": [
      {
        "from": [
          "__ToBeUpdated__::uberon:0010393"
        ],
        "fromBlank": false,
        "fromError": false,
        "to": "cl:0000895"
      }
    ],
    "description": "Mass edit cells in column sample_ontology_term"
  },
  {
    "op": "core/mass-edit",
    "engineConfig": {
      "facets": [
        {
          "type": "list",
          "name": "cell_type",
          "expression": "value",
          "columnName": "cell_type",
          "invert": false,
          "omitBlank": false,
          "omitError": false,
          "selection": [
            {
              "v": {
                "v": "naive cd4+ t cells",
                "l": "naive cd4+ t cells"
              }
            }
          ],
          "selectBlank": false,
          "selectError": false
        }
      ],
      "mode": "row-based"
    },
    "columnName": "sample_ontology_term",
    "expression": "value",
    "edits": [
      {
        "from": [
          "uberon:0010393::uberon:0012168"
        ],
        "fromBlank": false,
        "fromError": false,
        "to": "cl:0000895::uberon:0012168"
      }
    ],
    "description": "Mass edit cells in column sample_ontology_term"
  },
  {
    "op": "core/mass-edit",
    "engineConfig": {
      "facets": [
        {
          "type": "list",
          "name": "cell_type",
          "expression": "value",
          "columnName": "cell_type",
          "invert": false,
          "omitBlank": false,
          "omitError": false,
          "selection": [
            {
              "v": {
                "v": "naive cd4+ t cells",
                "l": "naive cd4+ t cells"
              }
            }
          ],
          "selectBlank": false,
          "selectError": false
        },
        {
          "type": "list",
          "name": "EpiRR",
          "expression": "value",
          "columnName": "EpiRR",
          "invert": false,
          "omitBlank": false,
          "omitError": false,
          "selection": [
            {
              "v": {
                "v": "IHECRE00004725.1",
                "l": "IHECRE00004725.1"
              }
            }
          ],
          "selectBlank": false,
          "selectError": false
        }
      ],
      "mode": "row-based"
    },
    "columnName": "tissue_type",
    "expression": "value",
    "edits": [
      {
        "from": [],
        "fromBlank": true,
        "fromError": false,
        "to": "umbilical cord blood"
      }
    ],
    "description": "Mass edit cells in column tissue_type"
  },
  {
    "op": "core/mass-edit",
    "engineConfig": {
      "facets": [
        {
          "type": "list",
          "name": "cell_type",
          "expression": "value",
          "columnName": "cell_type",
          "invert": false,
          "omitBlank": false,
          "omitError": false,
          "selection": [
            {
              "v": {
                "v": "naive cd4+ t cells",
                "l": "naive cd4+ t cells"
              }
            }
          ],
          "selectBlank": false,
          "selectError": false
        },
        {
          "type": "list",
          "name": "EpiRR",
          "expression": "value",
          "columnName": "EpiRR",
          "invert": false,
          "omitBlank": false,
          "omitError": false,
          "selection": [
            {
              "v": {
                "v": "IHECRE00004725.1",
                "l": "IHECRE00004725.1"
              }
            }
          ],
          "selectBlank": false,
          "selectError": false
        }
      ],
      "mode": "row-based"
    },
    "columnName": "origin_sample",
    "expression": "value",
    "edits": [
      {
        "from": [
          "Blood-Cord"
        ],
        "fromBlank": false,
        "fromError": false,
        "to": "umbilical cord blood"
      }
    ],
    "description": "Mass edit cells in column origin_sample"
  },
  {
    "op": "core/mass-edit",
    "engineConfig": {
      "facets": [],
      "mode": "row-based"
    },
    "columnName": "cell_type",
    "expression": "value",
    "edits": [
      {
        "from": [
          "naive cd4+ t cells"
        ],
        "fromBlank": false,
        "fromError": false,
        "to": "naive thymus-derived CD4-positive, alpha-beta T cell"
      }
    ],
    "description": "Mass edit cells in column cell_type"
  }
]